hext/__init__.py
hext/_hext.so
hext-1.0.14.data/scripts/htmlext
hext-1.0.14.dist-info/METADATA
hext-1.0.14.dist-info/WHEEL
hext-1.0.14.dist-info/top_level.txt
hext-1.0.14.dist-info/RECORD
