Metadata-Version: 2.4
Name: hext
Version: 1.0.14
Summary: A module and command-line utility to extract structured data from HTML
Home-page: https://hext.thomastrapp.com/
Author: Thomas Trapp
Author-email: hext@thomastrapp.com
License: Apache-2.0
Project-URL: Github, https://github.com/html-extract/hext/
Project-URL: Bug Reports, https://github.com/html-extract/hext/issues
Project-URL: Author, https://thomastrapp.com/
Keywords: html-extraction scraping html data-extraction
Classifier: Development Status :: 5 - Production/Stable
Classifier: Intended Audience :: Developers
Classifier: Operating System :: POSIX :: Linux
Classifier: Operating System :: MacOS :: MacOS X
Classifier: Programming Language :: C++
Classifier: Topic :: Internet :: WWW/HTTP
Classifier: Topic :: Software Development :: Libraries :: Python Modules
Dynamic: author
Dynamic: author-email
Dynamic: classifier
Dynamic: description
Dynamic: description-content-type
Dynamic: home-page
Dynamic: keywords
Dynamic: license
Dynamic: project-url
Dynamic: summary
